aiqa/__init__.py
aiqa/client.py
aiqa/constants.py
aiqa/experiment_runner.py
aiqa/http_utils.py
aiqa/llm_as_judge.py
aiqa/object_serialiser.py
aiqa/py.typed
aiqa/span_helpers.py
aiqa/tracing.py
aiqa/tracing_llm_utils.py
aiqa/types.py
aiqa_client-0.6.1.dist-info/licenses/LICENSE.txt
aiqa_client-0.6.1.dist-info/METADATA
aiqa_client-0.6.1.dist-info/WHEEL
aiqa_client-0.6.1.dist-info/top_level.txt
aiqa_client-0.6.1.dist-info/RECORD
