Metadata-Version: 2.4
Name: aiqa-client
Version: 0.6.1
Summary: OpenTelemetry-based Python client for tracing functions and sending traces to the AIQA server
Author-email: AIQA <info@aiqa.dev>
License: MIT
Project-URL: Homepage, https://github.com/winterwell/aiqa-client-python
Project-URL: Documentation, https://github.com/winterwell/aiqa-client-python
Project-URL: Repository, https://github.com/winterwell/aiqa-client-python
Project-URL: Issues, https://github.com/winterwell/aiqa-client-python/issues
Keywords: opentelemetry,tracing,observability,aiqa,monitoring
Classifier: Development Status :: 4 - Beta
Classifier: Intended Audience :: Developers
Classifier: License :: OSI Approved :: MIT License
Classifier: Programming Language :: Python :: 3
Classifier: Programming Language :: Python :: 3.8
Classifier: Programming Language :: Python :: 3.9
Classifier: Programming Language :: Python :: 3.10
Classifier: Programming Language :: Python :: 3.11
Classifier: Programming Language :: Python :: 3.12
Classifier: Topic :: Software Development :: Libraries :: Python Modules
Classifier: Topic :: System :: Monitoring
Requires-Python: >=3.8
License-File: LICENSE.txt
Requires-Dist: opentelemetry-api>=1.24.0
Requires-Dist: opentelemetry-sdk>=1.24.0
Requires-Dist: opentelemetry-semantic-conventions>=0.40b0
Requires-Dist: aiohttp>=3.9.0
Requires-Dist: requests>=2.31.0
Provides-Extra: dev
Requires-Dist: pytest>=7.0.0; extra == "dev"
Requires-Dist: pytest-asyncio>=0.21.0; extra == "dev"
Requires-Dist: black>=23.0.0; extra == "dev"
Requires-Dist: ruff>=0.1.0; extra == "dev"
Dynamic: license-file
